singletons/__init__.py
singletons/exceptions.py
singletons/factory.py
singletons/shared_module.py
singletons/singleton.py
singletons/utils.py
singletons-0.2.5.dist-info/LICENSE
singletons-0.2.5.dist-info/WHEEL
singletons-0.2.5.dist-info/METADATA
singletons-0.2.5.dist-info/RECORD
